deployer/__init__.py
deployer/deployer.py
deployer/download.py
deployer/main.py
gitlab_deployer-0.1.8.dist-info/entry_points.txt
gitlab_deployer-0.1.8.dist-info/LICENSE
gitlab_deployer-0.1.8.dist-info/WHEEL
gitlab_deployer-0.1.8.dist-info/METADATA
gitlab_deployer-0.1.8.dist-info/RECORD
